neutrino_client/__init__.py
neutrino_client/client.py
neutrino_client/neutrino_task.py
neutrino_client/task_pb2.py
neutrino_client/task_pb2.pyi
neutrino_client/task_pb2_grpc.py
neutrino_client-0.0.6.dist-info/METADATA
neutrino_client-0.0.6.dist-info/WHEEL
neutrino_client-0.0.6.dist-info/top_level.txt
neutrino_client-0.0.6.dist-info/RECORD
