Metadata-Version: 2.1
Name: neutrino_client
Version: 0.0.6
Summary: Neutrino client SDK
Author: dpdzero
Classifier: Programming Language :: Python :: 3
Classifier: Programming Language :: Python :: 3.11
Classifier: Operating System :: OS Independent
Requires-Dist: grpcio
Requires-Dist: grpcio-tools
Requires-Dist: protobuf
Requires-Dist: pydantic
